{
    "test.test_class_weights": {
        "checksum": "6b058686066f2da82160d6830af3aec2",
        "uri": "file://test.test_class_weights/model.bin"
    },
    "test.test_classification_ctr": {
        "checksum": "c032866906b8a9cd36e86dc4c94206dc",
        "uri": "file://test.test_classification_ctr/model.bin"
    },
    "test.test_copy_model": {
        "checksum": "22113101052aa91c025bcab017c9a073",
        "uri": "file://test.test_copy_model/model.bin"
    },
    "test.test_doc_feature_importance": {
        "checksum": "90670716082661a4217a9e73e0468ec8",
        "uri": "file://test.test_doc_feature_importance/feature_importance.npy"
    },
    "test.test_feature_importance": {
        "checksum": "0eabf84171b4c213f475f7de9ffa96ea",
        "uri": "file://test.test_feature_importance/feature_importance.npy"
    },
    "test.test_fit_data": {
        "checksum": "d107e279ef3d813d828beea38c9c5b46",
        "uri": "file://test.test_fit_data/model.bin"
    },
    "test.test_full_history": {
        "checksum": "48959264607bac1e3adc196e9f419a69",
        "uri": "file://test.test_full_history/model.bin"
    },
    "test.test_ignored_features": {
        "checksum": "3a19654dace238c34a92892f5603c55b",
        "uri": "file://test.test_ignored_features/model.bin"
    },
    "test.test_interaction_feature_importance": {
        "checksum": "1c25f29014764765e19b6b3429f4f0ac",
        "uri": "file://test.test_interaction_feature_importance/feature_importance.npy"
    },
    "test.test_multiclass": {
        "checksum": "8e1fd341bb19c88b4554512624e9bf05",
        "uri": "file://test.test_multiclass/predictions.npy"
    },
    "test.test_non_ones_weight": {
        "checksum": "265f51ea48d7be0cc3f62bd5731bfa73",
        "uri": "file://test.test_non_ones_weight/model.bin"
    },
    "test.test_ntree_limit": {
        "checksum": "6ef5da85edd929f38142403e91cf902a",
        "uri": "file://test.test_ntree_limit/predictions.npy"
    },
    "test.test_od": {
        "checksum": "b8eeba09daa98c6b6e7e025172476618",
        "uri": "file://test.test_od/model.bin"
    },
    "test.test_one_doc_feature_importance": {
        "checksum": "b96f50d250ca23a01b10ee26fc0b144d",
        "uri": "file://test.test_one_doc_feature_importance/feature_importance.npy"
    },
    "test.test_ones_weight": {
        "checksum": "e5d823ca87238f92013727ffd9c245e6",
        "uri": "file://test.test_ones_weight/model.bin"
    },
    "test.test_predict_class": {
        "checksum": "ab07dca84aa99741193fe2ea6ad1a1da",
        "uri": "file://test.test_predict_class/predictions.npy"
    },
    "test.test_predict_class_proba": {
        "checksum": "b49cebe88def3b66b612054ed911bea9",
        "uri": "file://test.test_predict_class_proba/predictions.npy"
    },
    "test.test_predict_class_raw": {
        "checksum": "ab07dca84aa99741193fe2ea6ad1a1da",
        "uri": "file://test.test_predict_class_raw/predictions.npy"
    },
    "test.test_predict_regress": {
        "checksum": "033a1eb835cf68b0eb24760e7d2ed9a8",
        "uri": "file://test.test_predict_regress/model.bin"
    },
    "test.test_predict_sklearn_class": {
        "checksum": "35731adcafd368e66d5aa72214733619",
        "uri": "file://test.test_predict_sklearn_class/model.bin"
    },
    "test.test_predict_sklearn_regress": {
        "checksum": "033a1eb835cf68b0eb24760e7d2ed9a8",
        "uri": "file://test.test_predict_sklearn_regress/model.bin"
    },
    "test.test_priors": {
        "checksum": "424b97ff500670125e8dfd3f986bee51",
        "uri": "file://test.test_priors/model.bin"
    },
    "test.test_regression_ctr": {
        "checksum": "78b1060d39fb45faf9ec9906e04fb2f0",
        "uri": "file://test.test_regression_ctr/model.bin"
    },
    "test.test_staged_predict": {
        "checksum": "718cf59d5f8ce7e4b7cf7fadb501032c",
        "uri": "file://test.test_staged_predict/predictions.npy"
    },
    "test.test_zero_baseline": {
        "checksum": "b9381d7bdfd9099b1c1d08b35e4b9f02",
        "uri": "file://test.test_zero_baseline/model.bin"
    }
}