{
  "meta": {"build":"CATBOOST_MLX_STAGE_PROFILE=ON","source":"csv_train","num_iterations":50,"grow_policy":"SymmetricTree","max_depth":6,"approx_dim":1,"num_docs":10000},
  "stage_names": ["derivatives_ms", "init_partitions_ms", "partition_layout_ms", "histogram_ms", "suffix_scoring_ms", "leaf_sums_ms", "leaf_values_ms", "tree_apply_ms", "loss_eval_ms", "cpu_readback_ms"],
  "iterations": [
    {
      "iter": 0,
      "derivatives_ms": 6.13837,
      "init_partitions_ms": 0,
      "partition_layout_ms": 1.82533,
      "histogram_ms": 25.0767,
      "suffix_scoring_ms": 1.51563,
      "leaf_sums_ms": 0.264167,
      "leaf_values_ms": 0.288167,
      "tree_apply_ms": 0.419125,
      "loss_eval_ms": 0.434791,
      "cpu_readback_ms": 0.49475,
      "depth_stages": [
        {"depth": 0, "partition_layout_ms": 0.629041, "histogram_ms": 7.57517, "histogram_perdim_max_ms": 0, "suffix_scoring_ms": 0.08375, "cpu_readback_ms": 0.008208},
        {"depth": 1, "partition_layout_ms": 0.250541, "histogram_ms": 1.99329, "histogram_perdim_max_ms": 0, "suffix_scoring_ms": 0.089, "cpu_readback_ms": 0.010792},
        {"depth": 2, "partition_layout_ms": 0.203917, "histogram_ms": 1.89792, "histogram_perdim_max_ms": 0, "suffix_scoring_ms": 0.1215, "cpu_readback_ms": 0.030333},
        {"depth": 3, "partition_layout_ms": 0.196584, "histogram_ms": 3.13921, "histogram_perdim_max_ms": 0, "suffix_scoring_ms": 0.203792, "cpu_readback_ms": 0.075625},
        {"depth": 4, "partition_layout_ms": 0.201125, "histogram_ms": 4.42075, "histogram_perdim_max_ms": 0, "suffix_scoring_ms": 0.368834, "cpu_readback_ms": 0.112542},
        {"depth": 5, "partition_layout_ms": 0.344125, "histogram_ms": 6.05033, "histogram_perdim_max_ms": 0, "suffix_scoring_ms": 0.64875, "cpu_readback_ms": 0.25725}
      ],
      "iter_total_ms": 38.2968
    },
    {
      "iter": 1,
      "derivatives_ms": 0.159125,
      "init_partitions_ms": 0,
      "partition_layout_ms": 1.18879,
      "histogram_ms": 19.7275,
      "suffix_scoring_ms": 1.55742,
      "leaf_sums_ms": 0.198708,
      "leaf_values_ms": 0.134458,
      "tree_apply_ms": 0.195541,
      "loss_eval_ms": 0.27025,
      "cpu_readback_ms": 0.078375,
      "depth_stages": [
        {"depth": 0, "partition_layout_ms": 0.197875, "histogram_ms": 1.91317, "histogram_perdim_max_ms": 0, "suffix_scoring_ms": 0.075917, "cpu_readback_ms": 0.002875},
        {"depth": 1, "partition_layout_ms": 0.176375, "histogram_ms": 2.06829, "histogram_perdim_max_ms": 0, "suffix_scoring_ms": 0.089083, "cpu_readback_ms": 0.004083},
        {"depth": 2, "partition_layout_ms": 0.203167, "histogram_ms": 2.19212, "histogram_perdim_max_ms": 0, "suffix_scoring_ms": 0.12125, "cpu_readback_ms": 0.016292},
        {"depth": 3, "partition_layout_ms": 0.19725, "histogram_ms": 3.3275, "histogram_perdim_max_ms": 0, "suffix_scoring_ms": 0.201959, "cpu_readback_ms": 0.009834},
        {"depth": 4, "partition_layout_ms": 0.207791, "histogram_ms": 4.0775, "histogram_perdim_max_ms": 0, "suffix_scoring_ms": 0.364042, "cpu_readback_ms": 0.015458},
        {"depth": 5, "partition_layout_ms": 0.206334, "histogram_ms": 6.14892, "histogram_perdim_max_ms": 0, "suffix_scoring_ms": 0.705166, "cpu_readback_ms": 0.029833}
      ],
      "iter_total_ms": 24.6973
    },
    {
      "iter": 2,
      "derivatives_ms": 2.86587,
      "init_partitions_ms": 0,
      "partition_layout_ms": 1.18271,
      "histogram_ms": 20.9216,
      "suffix_scoring_ms": 1.56708,
      "leaf_sums_ms": 0.19625,
      "leaf_values_ms": 0.205,
      "tree_apply_ms": 0.174542,
      "loss_eval_ms": 0.204125,
      "cpu_readback_ms": 0.157917,
      "depth_stages": [
        {"depth": 0, "partition_layout_ms": 0.224833, "histogram_ms": 1.91196, "histogram_perdim_max_ms": 0, "suffix_scoring_ms": 0.0785, "cpu_readback_ms": 0.004709},
        {"depth": 1, "partition_layout_ms": 0.212709, "histogram_ms": 2.06304, "histogram_perdim_max_ms": 0, "suffix_scoring_ms": 0.087834, "cpu_readback_ms": 0.003625},
        {"depth": 2, "partition_layout_ms": 0.151292, "histogram_ms": 1.97571, "histogram_perdim_max_ms": 0, "suffix_scoring_ms": 0.119166, "cpu_readback_ms": 0.009042},
        {"depth": 3, "partition_layout_ms": 0.168042, "histogram_ms": 3.30492, "histogram_perdim_max_ms": 0, "suffix_scoring_ms": 0.20525, "cpu_readback_ms": 0.009333},
        {"depth": 4, "partition_layout_ms": 0.209083, "histogram_ms": 4.30533, "histogram_perdim_max_ms": 0, "suffix_scoring_ms": 0.397667, "cpu_readback_ms": 0.021208},
        {"depth": 5, "partition_layout_ms": 0.21675, "histogram_ms": 7.36062, "histogram_perdim_max_ms": 0, "suffix_scoring_ms": 0.678667, "cpu_readback_ms": 0.11}
      ],
      "iter_total_ms": 28.7773
    },
    {
      "iter": 3,
      "derivatives_ms": 0.179625,
      "init_partitions_ms": 0,
      "partition_layout_ms": 1.19787,
      "histogram_ms": 22.1939,
      "suffix_scoring_ms": 1.55387,
      "leaf_sums_ms": 0.176166,
      "leaf_values_ms": 0.2025,
      "tree_apply_ms": 0.198209,
      "loss_eval_ms": 0.255042,
      "cpu_readback_ms": 0.070292,
      "depth_stages": [
        {"depth": 0, "partition_layout_ms": 0.178333, "histogram_ms": 1.82629, "histogram_perdim_max_ms": 0, "suffix_scoring_ms": 0.071625, "cpu_readback_ms": 0.002375},
        {"depth": 1, "partition_layout_ms": 0.162125, "histogram_ms": 2.06958, "histogram_perdim_max_ms": 0, "suffix_scoring_ms": 0.092583, "cpu_readback_ms": 0.002833},
        {"depth": 2, "partition_layout_ms": 0.201584, "histogram_ms": 1.92525, "histogram_perdim_max_ms": 0, "suffix_scoring_ms": 0.140875, "cpu_readback_ms": 0.005334},
        {"depth": 3, "partition_layout_ms": 0.220208, "histogram_ms": 3.51487, "histogram_perdim_max_ms": 0, "suffix_scoring_ms": 0.229166, "cpu_readback_ms": 0.009458},
        {"depth": 4, "partition_layout_ms": 0.25725, "histogram_ms": 5.43667, "histogram_perdim_max_ms": 0, "suffix_scoring_ms": 0.37225, "cpu_readback_ms": 0.0205},
        {"depth": 5, "partition_layout_ms": 0.178375, "histogram_ms": 7.42121, "histogram_perdim_max_ms": 0, "suffix_scoring_ms": 0.647375, "cpu_readback_ms": 0.029792}
      ],
      "iter_total_ms": 27.2055
    },
    {
      "iter": 4,
      "derivatives_ms": 0.157833,
      "init_partitions_ms": 0,
      "partition_layout_ms": 1.57533,
      "histogram_ms": 22.353,
      "suffix_scoring_ms": 1.55425,
      "leaf_sums_ms": 0.218667,
      "leaf_values_ms": 0.208583,
      "tree_apply_ms": 0.217042,
      "loss_eval_ms": 0.225541,
      "cpu_readback_ms": 0.07979,
      "depth_stages": [
        {"depth": 0, "partition_layout_ms": 0.33475, "histogram_ms": 2.00617, "histogram_perdim_max_ms": 0, "suffix_scoring_ms": 0.092458, "cpu_readback_ms": 0.004166},
        {"depth": 1, "partition_layout_ms": 0.233166, "histogram_ms": 2.06021, "histogram_perdim_max_ms": 0, "suffix_scoring_ms": 0.093666, "cpu_readback_ms": 0.004},
        {"depth": 2, "partition_layout_ms": 0.313667, "histogram_ms": 1.96538, "histogram_perdim_max_ms": 0, "suffix_scoring_ms": 0.133375, "cpu_readback_ms": 0.00625},
        {"depth": 3, "partition_layout_ms": 0.226375, "histogram_ms": 3.36704, "histogram_perdim_max_ms": 0, "suffix_scoring_ms": 0.215959, "cpu_readback_ms": 0.010125},
        {"depth": 4, "partition_layout_ms": 0.235458, "histogram_ms": 5.38808, "histogram_perdim_max_ms": 0, "suffix_scoring_ms": 0.333417, "cpu_readback_ms": 0.020833},
        {"depth": 5, "partition_layout_ms": 0.231916, "histogram_ms": 7.56617, "histogram_perdim_max_ms": 0, "suffix_scoring_ms": 0.685375, "cpu_readback_ms": 0.034416}
      ],
      "iter_total_ms": 28.0757
    },
    {
      "iter": 5,
      "derivatives_ms": 0.166666,
      "init_partitions_ms": 0,
      "partition_layout_ms": 1.61687,
      "histogram_ms": 23.1015,
      "suffix_scoring_ms": 1.55604,
      "leaf_sums_ms": 0.253334,
      "leaf_values_ms": 0.211083,
      "tree_apply_ms": 0.205458,
      "loss_eval_ms": 0.235791,
      "cpu_readback_ms": 0.075917,
      "depth_stages": [
        {"depth": 0, "partition_layout_ms": 0.229208, "histogram_ms": 1.927, "histogram_perdim_max_ms": 0, "suffix_scoring_ms": 0.076875, "cpu_readback_ms": 0.002625},
        {"depth": 1, "partition_layout_ms": 0.288417, "histogram_ms": 2.02304, "histogram_perdim_max_ms": 0, "suffix_scoring_ms": 0.102958, "cpu_readback_ms": 0.003958},
        {"depth": 2, "partition_layout_ms": 0.238833, "histogram_ms": 2.08692, "histogram_perdim_max_ms": 0, "suffix_scoring_ms": 0.127709, "cpu_readback_ms": 0.006167},
        {"depth": 3, "partition_layout_ms": 0.258416, "histogram_ms": 3.35908, "histogram_perdim_max_ms": 0, "suffix_scoring_ms": 0.208084, "cpu_readback_ms": 0.011},
        {"depth": 4, "partition_layout_ms": 0.265125, "histogram_ms": 6.1465, "histogram_perdim_max_ms": 0, "suffix_scoring_ms": 0.347667, "cpu_readback_ms": 0.018542},
        {"depth": 5, "partition_layout_ms": 0.336875, "histogram_ms": 7.55896, "histogram_perdim_max_ms": 0, "suffix_scoring_ms": 0.69275, "cpu_readback_ms": 0.033625}
      ],
      "iter_total_ms": 28.9464
    },
    {
      "iter": 6,
      "derivatives_ms": 0.220958,
      "init_partitions_ms": 0,
      "partition_layout_ms": 1.45658,
      "histogram_ms": 23.1557,
      "suffix_scoring_ms": 1.64429,
      "leaf_sums_ms": 0.223417,
      "leaf_values_ms": 0.212333,
      "tree_apply_ms": 0.195792,
      "loss_eval_ms": 0.244917,
      "cpu_readback_ms": 0.079167,
      "depth_stages": [
        {"depth": 0, "partition_layout_ms": 0.217917, "histogram_ms": 2.58108, "histogram_perdim_max_ms": 0, "suffix_scoring_ms": 0.076291, "cpu_readback_ms": 0.004083},
        {"depth": 1, "partition_layout_ms": 0.262208, "histogram_ms": 2.14787, "histogram_perdim_max_ms": 0, "suffix_scoring_ms": 0.090333, "cpu_readback_ms": 0.004333},
        {"depth": 2, "partition_layout_ms": 0.236333, "histogram_ms": 1.93421, "histogram_perdim_max_ms": 0, "suffix_scoring_ms": 0.145625, "cpu_readback_ms": 0.005917},
        {"depth": 3, "partition_layout_ms": 0.249583, "histogram_ms": 3.30225, "histogram_perdim_max_ms": 0, "suffix_scoring_ms": 0.215959, "cpu_readback_ms": 0.009209},
        {"depth": 4, "partition_layout_ms": 0.252792, "histogram_ms": 5.56142, "histogram_perdim_max_ms": 0, "suffix_scoring_ms": 0.391167, "cpu_readback_ms": 0.019417},
        {"depth": 5, "partition_layout_ms": 0.23775, "histogram_ms": 7.62887, "histogram_perdim_max_ms": 0, "suffix_scoring_ms": 0.724917, "cpu_readback_ms": 0.036208}
      ],
      "iter_total_ms": 28.965
    },
    {
      "iter": 7,
      "derivatives_ms": 0.23025,
      "init_partitions_ms": 0,
      "partition_layout_ms": 1.42292,
      "histogram_ms": 18.6382,
      "suffix_scoring_ms": 1.60404,
      "leaf_sums_ms": 0.193958,
      "leaf_values_ms": 0.218667,
      "tree_apply_ms": 0.170792,
      "loss_eval_ms": 0.260833,
      "cpu_readback_ms": 0.091624,
      "depth_stages": [
        {"depth": 0, "partition_layout_ms": 0.245125, "histogram_ms": 1.94242, "histogram_perdim_max_ms": 0, "suffix_scoring_ms": 0.071917, "cpu_readback_ms": 0.002833},
        {"depth": 1, "partition_layout_ms": 0.214583, "histogram_ms": 2.07996, "histogram_perdim_max_ms": 0, "suffix_scoring_ms": 0.099042, "cpu_readback_ms": 0.010333},
        {"depth": 2, "partition_layout_ms": 0.278458, "histogram_ms": 1.94746, "histogram_perdim_max_ms": 0, "suffix_scoring_ms": 0.135916, "cpu_readback_ms": 0.00575},
        {"depth": 3, "partition_layout_ms": 0.230292, "histogram_ms": 2.96675, "histogram_perdim_max_ms": 0, "suffix_scoring_ms": 0.221042, "cpu_readback_ms": 0.012083},
        {"depth": 4, "partition_layout_ms": 0.221792, "histogram_ms": 4.32475, "histogram_perdim_max_ms": 0, "suffix_scoring_ms": 0.390083, "cpu_readback_ms": 0.024167},
        {"depth": 5, "partition_layout_ms": 0.232667, "histogram_ms": 5.37683, "histogram_perdim_max_ms": 0, "suffix_scoring_ms": 0.686042, "cpu_readback_ms": 0.036458}
      ],
      "iter_total_ms": 24.4673
    },
    {
      "iter": 8,
      "derivatives_ms": 0.212917,
      "init_partitions_ms": 0,
      "partition_layout_ms": 1.61971,
      "histogram_ms": 22.4352,
      "suffix_scoring_ms": 1.52404,
      "leaf_sums_ms": 0.219709,
      "leaf_values_ms": 0.271041,
      "tree_apply_ms": 0.236,
      "loss_eval_ms": 0.217333,
      "cpu_readback_ms": 0.079417,
      "depth_stages": [
        {"depth": 0, "partition_layout_ms": 0.297542, "histogram_ms": 2.06383, "histogram_perdim_max_ms": 0, "suffix_scoring_ms": 0.072458, "cpu_readback_ms": 0.004},
        {"depth": 1, "partition_layout_ms": 0.290292, "histogram_ms": 2.09896, "histogram_perdim_max_ms": 0, "suffix_scoring_ms": 0.087333, "cpu_readback_ms": 0.005},
        {"depth": 2, "partition_layout_ms": 0.234541, "histogram_ms": 2.11713, "histogram_perdim_max_ms": 0, "suffix_scoring_ms": 0.122333, "cpu_readback_ms": 0.00575},
        {"depth": 3, "partition_layout_ms": 0.256459, "histogram_ms": 3.43575, "histogram_perdim_max_ms": 0, "suffix_scoring_ms": 0.19825, "cpu_readback_ms": 0.012084},
        {"depth": 4, "partition_layout_ms": 0.242458, "histogram_ms": 5.33142, "histogram_perdim_max_ms": 0, "suffix_scoring_ms": 0.35225, "cpu_readback_ms": 0.020125},
        {"depth": 5, "partition_layout_ms": 0.298417, "histogram_ms": 7.38812, "histogram_perdim_max_ms": 0, "suffix_scoring_ms": 0.691416, "cpu_readback_ms": 0.032458}
      ],
      "iter_total_ms": 28.5086
    },
    {
      "iter": 9,
      "derivatives_ms": 0.183209,
      "init_partitions_ms": 0,
      "partition_layout_ms": 1.56421,
      "histogram_ms": 23.9685,
      "suffix_scoring_ms": 1.71925,
      "leaf_sums_ms": 0.236375,
      "leaf_values_ms": 0.227583,
      "tree_apply_ms": 0.255584,
      "loss_eval_ms": 0.273208,
      "cpu_readback_ms": 0.078166,
      "depth_stages": [
        {"depth": 0, "partition_layout_ms": 0.282375, "histogram_ms": 1.93796, "histogram_perdim_max_ms": 0, "suffix_scoring_ms": 0.08375, "cpu_readback_ms": 0.002834},
        {"depth": 1, "partition_layout_ms": 0.370875, "histogram_ms": 2.04, "histogram_perdim_max_ms": 0, "suffix_scoring_ms": 0.089333, "cpu_readback_ms": 0.003583},
        {"depth": 2, "partition_layout_ms": 0.192625, "histogram_ms": 2.14517, "histogram_perdim_max_ms": 0, "suffix_scoring_ms": 0.1365, "cpu_readback_ms": 0.007708},
        {"depth": 3, "partition_layout_ms": 0.212834, "histogram_ms": 3.422, "histogram_perdim_max_ms": 0, "suffix_scoring_ms": 0.22575, "cpu_readback_ms": 0.008833},
        {"depth": 4, "partition_layout_ms": 0.262416, "histogram_ms": 5.24867, "histogram_perdim_max_ms": 0, "suffix_scoring_ms": 0.413875, "cpu_readback_ms": 0.016125},
        {"depth": 5, "partition_layout_ms": 0.243083, "histogram_ms": 9.17467, "histogram_perdim_max_ms": 0, "suffix_scoring_ms": 0.770041, "cpu_readback_ms": 0.039083}
      ],
      "iter_total_ms": 30.1133
    },
    {
      "iter": 10,
      "derivatives_ms": 0.202791,
      "init_partitions_ms": 0,
      "partition_layout_ms": 1.49104,
      "histogram_ms": 22.9318,
      "suffix_scoring_ms": 1.56996,
      "leaf_sums_ms": 0.589542,
      "leaf_values_ms": 0.308917,
      "tree_apply_ms": 0.658709,
      "loss_eval_ms": 0.448167,
      "cpu_readback_ms": 0.231,
      "depth_stages": [
        {"depth": 0, "partition_layout_ms": 0.247166, "histogram_ms": 2.03454, "histogram_perdim_max_ms": 0, "suffix_scoring_ms": 0.077375, "cpu_readback_ms": 0.002917},
        {"depth": 1, "partition_layout_ms": 0.251459, "histogram_ms": 2.15279, "histogram_perdim_max_ms": 0, "suffix_scoring_ms": 0.092958, "cpu_readback_ms": 0.0085},
        {"depth": 2, "partition_layout_ms": 0.270042, "histogram_ms": 2.11104, "histogram_perdim_max_ms": 0, "suffix_scoring_ms": 0.126792, "cpu_readback_ms": 0.0045},
        {"depth": 3, "partition_layout_ms": 0.284166, "histogram_ms": 3.33892, "histogram_perdim_max_ms": 0, "suffix_scoring_ms": 0.20875, "cpu_readback_ms": 0.009959},
        {"depth": 4, "partition_layout_ms": 0.22625, "histogram_ms": 4.2375, "histogram_perdim_max_ms": 0, "suffix_scoring_ms": 0.375167, "cpu_readback_ms": 0.019541},
        {"depth": 5, "partition_layout_ms": 0.211958, "histogram_ms": 9.057, "histogram_perdim_max_ms": 0, "suffix_scoring_ms": 0.688917, "cpu_readback_ms": 0.185583}
      ],
      "iter_total_ms": 30.2097
    },
    {
      "iter": 11,
      "derivatives_ms": 0.462541,
      "init_partitions_ms": 0,
      "partition_layout_ms": 4.97996,
      "histogram_ms": 26.323,
      "suffix_scoring_ms": 1.54517,
      "leaf_sums_ms": 0.428792,
      "leaf_values_ms": 0.289333,
      "tree_apply_ms": 0.172083,
      "loss_eval_ms": 0.626916,
      "cpu_readback_ms": 0.08075,
      "depth_stages": [
        {"depth": 0, "partition_layout_ms": 0.54575, "histogram_ms": 2.32967, "histogram_perdim_max_ms": 0, "suffix_scoring_ms": 0.105584, "cpu_readback_ms": 0.007042},
        {"depth": 1, "partition_layout_ms": 0.427208, "histogram_ms": 2.46529, "histogram_perdim_max_ms": 0, "suffix_scoring_ms": 0.088333, "cpu_readback_ms": 0.004167},
        {"depth": 2, "partition_layout_ms": 0.369875, "histogram_ms": 3.12946, "histogram_perdim_max_ms": 0, "suffix_scoring_ms": 0.122916, "cpu_readback_ms": 0.008125},
        {"depth": 3, "partition_layout_ms": 2.22629, "histogram_ms": 3.94025, "histogram_perdim_max_ms": 0, "suffix_scoring_ms": 0.213166, "cpu_readback_ms": 0.010083},
        {"depth": 4, "partition_layout_ms": 0.72575, "histogram_ms": 5.86137, "histogram_perdim_max_ms": 0, "suffix_scoring_ms": 0.3465, "cpu_readback_ms": 0.017583},
        {"depth": 5, "partition_layout_ms": 0.685084, "histogram_ms": 8.597, "histogram_perdim_max_ms": 0, "suffix_scoring_ms": 0.668667, "cpu_readback_ms": 0.03375}
      ],
      "iter_total_ms": 45.6976
    },
    {
      "iter": 12,
      "derivatives_ms": 0.558333,
      "init_partitions_ms": 0,
      "partition_layout_ms": 3.70542,
      "histogram_ms": 27.2425,
      "suffix_scoring_ms": 2.24383,
      "leaf_sums_ms": 0.613417,
      "leaf_values_ms": 0.449667,
      "tree_apply_ms": 0.274625,
      "loss_eval_ms": 0.368417,
      "cpu_readback_ms": 0.149957,
      "depth_stages": [
        {"depth": 0, "partition_layout_ms": 0.524958, "histogram_ms": 2.44037, "histogram_perdim_max_ms": 0, "suffix_scoring_ms": 0.231084, "cpu_readback_ms": 0.007},
        {"depth": 1, "partition_layout_ms": 0.773959, "histogram_ms": 4.312, "histogram_perdim_max_ms": 0, "suffix_scoring_ms": 0.296, "cpu_readback_ms": 0.010208},
        {"depth": 2, "partition_layout_ms": 0.9655, "histogram_ms": 4.91229, "histogram_perdim_max_ms": 0, "suffix_scoring_ms": 0.26775, "cpu_readback_ms": 0.013541},
        {"depth": 3, "partition_layout_ms": 0.332, "histogram_ms": 3.62633, "histogram_perdim_max_ms": 0, "suffix_scoring_ms": 0.214208, "cpu_readback_ms": 0.010541},
        {"depth": 4, "partition_layout_ms": 0.263542, "histogram_ms": 4.9275, "histogram_perdim_max_ms": 0, "suffix_scoring_ms": 0.366375, "cpu_readback_ms": 0.017125},
        {"depth": 5, "partition_layout_ms": 0.845459, "histogram_ms": 7.02404, "histogram_perdim_max_ms": 0, "suffix_scoring_ms": 0.868417, "cpu_readback_ms": 0.091542}
      ],
      "iter_total_ms": 42.0806
    },
    {
      "iter": 13,
      "derivatives_ms": 0.388,
      "init_partitions_ms": 0,
      "partition_layout_ms": 3.75992,
      "histogram_ms": 28.5149,
      "suffix_scoring_ms": 1.92492,
      "leaf_sums_ms": 0.270416,
      "leaf_values_ms": 0.2365,
      "tree_apply_ms": 0.248583,
      "loss_eval_ms": 0.288,
      "cpu_readback_ms": 0.09225,
      "depth_stages": [
        {"depth": 0, "partition_layout_ms": 0.266416, "histogram_ms": 2.11525, "histogram_perdim_max_ms": 0, "suffix_scoring_ms": 0.156375, "cpu_readback_ms": 0.005833},
        {"depth": 1, "partition_layout_ms": 0.386292, "histogram_ms": 2.26783, "histogram_perdim_max_ms": 0, "suffix_scoring_ms": 0.087625, "cpu_readback_ms": 0.005292},
        {"depth": 2, "partition_layout_ms": 0.628625, "histogram_ms": 2.88817, "histogram_perdim_max_ms": 0, "suffix_scoring_ms": 0.17025, "cpu_readback_ms": 0.016417},
        {"depth": 3, "partition_layout_ms": 1.83404, "histogram_ms": 3.53104, "histogram_perdim_max_ms": 0, "suffix_scoring_ms": 0.203292, "cpu_readback_ms": 0.011791},
        {"depth": 4, "partition_layout_ms": 0.384083, "histogram_ms": 5.74092, "histogram_perdim_max_ms": 0, "suffix_scoring_ms": 0.351792, "cpu_readback_ms": 0.018542},
        {"depth": 5, "partition_layout_ms": 0.260458, "histogram_ms": 11.9717, "histogram_perdim_max_ms": 0, "suffix_scoring_ms": 0.955583, "cpu_readback_ms": 0.034375}
      ],
      "iter_total_ms": 42.3337
    },
    {
      "iter": 14,
      "derivatives_ms": 0.280708,
      "init_partitions_ms": 0,
      "partition_layout_ms": 1.83713,
      "histogram_ms": 21.6496,
      "suffix_scoring_ms": 1.61667,
      "leaf_sums_ms": 0.259667,
      "leaf_values_ms": 0.266875,
      "tree_apply_ms": 0.242583,
      "loss_eval_ms": 0.285125,
      "cpu_readback_ms": 0.08679,
      "depth_stages": [
        {"depth": 0, "partition_layout_ms": 0.305, "histogram_ms": 2.15096, "histogram_perdim_max_ms": 0, "suffix_scoring_ms": 0.073709, "cpu_readback_ms": 0.004375},
        {"depth": 1, "partition_layout_ms": 0.31125, "histogram_ms": 2.46058, "histogram_perdim_max_ms": 0, "suffix_scoring_ms": 0.088042, "cpu_readback_ms": 0.004792},
        {"depth": 2, "partition_layout_ms": 0.296375, "histogram_ms": 2.42492, "histogram_perdim_max_ms": 0, "suffix_scoring_ms": 0.119625, "cpu_readback_ms": 0.005833},
        {"depth": 3, "partition_layout_ms": 0.329125, "histogram_ms": 3.64588, "histogram_perdim_max_ms": 0, "suffix_scoring_ms": 0.237292, "cpu_readback_ms": 0.010291},
        {"depth": 4, "partition_layout_ms": 0.277334, "histogram_ms": 4.65787, "histogram_perdim_max_ms": 0, "suffix_scoring_ms": 0.423083, "cpu_readback_ms": 0.028833},
        {"depth": 5, "partition_layout_ms": 0.318042, "histogram_ms": 6.30942, "histogram_perdim_max_ms": 0, "suffix_scoring_ms": 0.674917, "cpu_readback_ms": 0.032666}
      ],
      "iter_total_ms": 28.3148
    },
    {
      "iter": 15,
      "derivatives_ms": 0.237333,
      "init_partitions_ms": 0,
      "partition_layout_ms": 1.84992,
      "histogram_ms": 25.1739,
      "suffix_scoring_ms": 1.63958,
      "leaf_sums_ms": 0.758292,
      "leaf_values_ms": 0.986417,
      "tree_apply_ms": 0.237042,
      "loss_eval_ms": 0.211667,
      "cpu_readback_ms": 0.19771,
      "depth_stages": [
        {"depth": 0, "partition_layout_ms": 0.259792, "histogram_ms": 2.20325, "histogram_perdim_max_ms": 0, "suffix_scoring_ms": 0.070292, "cpu_readback_ms": 0.003334},
        {"depth": 1, "partition_layout_ms": 0.278, "histogram_ms": 2.29883, "histogram_perdim_max_ms": 0, "suffix_scoring_ms": 0.086583, "cpu_readback_ms": 0.005125},
        {"depth": 2, "partition_layout_ms": 0.259167, "histogram_ms": 2.16729, "histogram_perdim_max_ms": 0, "suffix_scoring_ms": 0.148041, "cpu_readback_ms": 0.006083},
        {"depth": 3, "partition_layout_ms": 0.306375, "histogram_ms": 3.32308, "histogram_perdim_max_ms": 0, "suffix_scoring_ms": 0.24875, "cpu_readback_ms": 0.025334},
        {"depth": 4, "partition_layout_ms": 0.286583, "histogram_ms": 4.52346, "histogram_perdim_max_ms": 0, "suffix_scoring_ms": 0.355625, "cpu_readback_ms": 0.017167},
        {"depth": 5, "partition_layout_ms": 0.46, "histogram_ms": 10.658, "histogram_perdim_max_ms": 0, "suffix_scoring_ms": 0.730292, "cpu_readback_ms": 0.140667}
      ],
      "iter_total_ms": 37.7142
    },
    {
      "iter": 16,
      "derivatives_ms": 0.1875,
      "init_partitions_ms": 0,
      "partition_layout_ms": 2.33833,
      "histogram_ms": 26.5145,
      "suffix_scoring_ms": 1.71017,
      "leaf_sums_ms": 0.230667,
      "leaf_values_ms": 0.275292,
      "tree_apply_ms": 0.211542,
      "loss_eval_ms": 0.370625,
      "cpu_readback_ms": 0.116708,
      "depth_stages": [
        {"depth": 0, "partition_layout_ms": 0.31575, "histogram_ms": 2.11867, "histogram_perdim_max_ms": 0, "suffix_scoring_ms": 0.072042, "cpu_readback_ms": 0.00325},
        {"depth": 1, "partition_layout_ms": 0.301334, "histogram_ms": 2.24042, "histogram_perdim_max_ms": 0, "suffix_scoring_ms": 0.130834, "cpu_readback_ms": 0.008125},
        {"depth": 2, "partition_layout_ms": 0.5005, "histogram_ms": 2.44208, "histogram_perdim_max_ms": 0, "suffix_scoring_ms": 0.120542, "cpu_readback_ms": 0.008208},
        {"depth": 3, "partition_layout_ms": 0.2995, "histogram_ms": 3.96483, "histogram_perdim_max_ms": 0, "suffix_scoring_ms": 0.200167, "cpu_readback_ms": 0.010458},
        {"depth": 4, "partition_layout_ms": 0.27275, "histogram_ms": 5.83954, "histogram_perdim_max_ms": 0, "suffix_scoring_ms": 0.488459, "cpu_readback_ms": 0.054917},
        {"depth": 5, "partition_layout_ms": 0.6485, "histogram_ms": 9.90892, "histogram_perdim_max_ms": 0, "suffix_scoring_ms": 0.698125, "cpu_readback_ms": 0.03175}
      ],
      "iter_total_ms": 33.9128
    },
    {
      "iter": 17,
      "derivatives_ms": 0.328042,
      "init_partitions_ms": 0,
      "partition_layout_ms": 2.03533,
      "histogram_ms": 25.7736,
      "suffix_scoring_ms": 2.09833,
      "leaf_sums_ms": 0.31075,
      "leaf_values_ms": 0.24925,
      "tree_apply_ms": 0.197875,
      "loss_eval_ms": 0.264458,
      "cpu_readback_ms": 0.223874,
      "depth_stages": [
        {"depth": 0, "partition_layout_ms": 0.278125, "histogram_ms": 2.05625, "histogram_perdim_max_ms": 0, "suffix_scoring_ms": 0.102375, "cpu_readback_ms": 0.007125},
        {"depth": 1, "partition_layout_ms": 0.232625, "histogram_ms": 2.21488, "histogram_perdim_max_ms": 0, "suffix_scoring_ms": 0.088083, "cpu_readback_ms": 0.006167},
        {"depth": 2, "partition_layout_ms": 0.36, "histogram_ms": 2.20467, "histogram_perdim_max_ms": 0, "suffix_scoring_ms": 0.122167, "cpu_readback_ms": 0.008041},
        {"depth": 3, "partition_layout_ms": 0.318959, "histogram_ms": 3.63192, "histogram_perdim_max_ms": 0, "suffix_scoring_ms": 0.611125, "cpu_readback_ms": 0.0235},
        {"depth": 4, "partition_layout_ms": 0.342166, "histogram_ms": 5.96621, "histogram_perdim_max_ms": 0, "suffix_scoring_ms": 0.46625, "cpu_readback_ms": 0.066916},
        {"depth": 5, "partition_layout_ms": 0.503459, "histogram_ms": 9.69967, "histogram_perdim_max_ms": 0, "suffix_scoring_ms": 0.708334, "cpu_readback_ms": 0.112125}
      ],
      "iter_total_ms": 33.635
    },
    {
      "iter": 18,
      "derivatives_ms": 2.77933,
      "init_partitions_ms": 0,
      "partition_layout_ms": 4.75054,
      "histogram_ms": 32.1678,
      "suffix_scoring_ms": 1.72225,
      "leaf_sums_ms": 0.189584,
      "leaf_values_ms": 0.228666,
      "tree_apply_ms": 0.244208,
      "loss_eval_ms": 0.236709,
      "cpu_readback_ms": 0.522708,
      "depth_stages": [
        {"depth": 0, "partition_layout_ms": 3.03587, "histogram_ms": 9.18512, "histogram_perdim_max_ms": 0, "suffix_scoring_ms": 0.244958, "cpu_readback_ms": 0.406333},
        {"depth": 1, "partition_layout_ms": 0.646417, "histogram_ms": 2.25888, "histogram_perdim_max_ms": 0, "suffix_scoring_ms": 0.10925, "cpu_readback_ms": 0.012625},
        {"depth": 2, "partition_layout_ms": 0.258125, "histogram_ms": 2.43929, "histogram_perdim_max_ms": 0, "suffix_scoring_ms": 0.132959, "cpu_readback_ms": 0.040834},
        {"depth": 3, "partition_layout_ms": 0.288167, "histogram_ms": 3.50546, "histogram_perdim_max_ms": 0, "suffix_scoring_ms": 0.205208, "cpu_readback_ms": 0.011},
        {"depth": 4, "partition_layout_ms": 0.272875, "histogram_ms": 5.34208, "histogram_perdim_max_ms": 0, "suffix_scoring_ms": 0.349042, "cpu_readback_ms": 0.015541},
        {"depth": 5, "partition_layout_ms": 0.249083, "histogram_ms": 9.437, "histogram_perdim_max_ms": 0, "suffix_scoring_ms": 0.680833, "cpu_readback_ms": 0.036375}
      ],
      "iter_total_ms": 47.5748
    },
    {
      "iter": 19,
      "derivatives_ms": 0.256042,
      "init_partitions_ms": 0,
      "partition_layout_ms": 1.56483,
      "histogram_ms": 24.48,
      "suffix_scoring_ms": 1.76929,
      "leaf_sums_ms": 0.234958,
      "leaf_values_ms": 0.139875,
      "tree_apply_ms": 0.232542,
      "loss_eval_ms": 0.259125,
      "cpu_readback_ms": 0.141,
      "depth_stages": [
        {"depth": 0, "partition_layout_ms": 0.270042, "histogram_ms": 1.94933, "histogram_perdim_max_ms": 0, "suffix_scoring_ms": 0.077625, "cpu_readback_ms": 0.002375},
        {"depth": 1, "partition_layout_ms": 0.237417, "histogram_ms": 2.09037, "histogram_perdim_max_ms": 0, "suffix_scoring_ms": 0.104083, "cpu_readback_ms": 0.004},
        {"depth": 2, "partition_layout_ms": 0.256416, "histogram_ms": 1.95612, "histogram_perdim_max_ms": 0, "suffix_scoring_ms": 0.130834, "cpu_readback_ms": 0.005375},
        {"depth": 3, "partition_layout_ms": 0.236833, "histogram_ms": 3.44654, "histogram_perdim_max_ms": 0, "suffix_scoring_ms": 0.360875, "cpu_readback_ms": 0.022958},
        {"depth": 4, "partition_layout_ms": 0.27175, "histogram_ms": 5.5635, "histogram_perdim_max_ms": 0, "suffix_scoring_ms": 0.352667, "cpu_readback_ms": 0.066292},
        {"depth": 5, "partition_layout_ms": 0.292375, "histogram_ms": 9.47408, "histogram_perdim_max_ms": 0, "suffix_scoring_ms": 0.743209, "cpu_readback_ms": 0.04}
      ],
      "iter_total_ms": 30.5855
    },
    {
      "iter": 20,
      "derivatives_ms": 0.218417,
      "init_partitions_ms": 0,
      "partition_layout_ms": 1.686,
      "histogram_ms": 24.3357,
      "suffix_scoring_ms": 1.56058,
      "leaf_sums_ms": 0.2255,
      "leaf_values_ms": 0.221083,
      "tree_apply_ms": 0.250791,
      "loss_eval_ms": 0.221958,
      "cpu_readback_ms": 0.078251,
      "depth_stages": [
        {"depth": 0, "partition_layout_ms": 0.299417, "histogram_ms": 2.025, "histogram_perdim_max_ms": 0, "suffix_scoring_ms": 0.074625, "cpu_readback_ms": 0.004375},
        {"depth": 1, "partition_layout_ms": 0.269875, "histogram_ms": 2.13163, "histogram_perdim_max_ms": 0, "suffix_scoring_ms": 0.096959, "cpu_readback_ms": 0.003625},
        {"depth": 2, "partition_layout_ms": 0.242083, "histogram_ms": 2.07313, "histogram_perdim_max_ms": 0, "suffix_scoring_ms": 0.125417, "cpu_readback_ms": 0.005292},
        {"depth": 3, "partition_layout_ms": 0.353583, "histogram_ms": 3.3305, "histogram_perdim_max_ms": 0, "suffix_scoring_ms": 0.21175, "cpu_readback_ms": 0.008917},
        {"depth": 4, "partition_layout_ms": 0.26725, "histogram_ms": 5.45467, "histogram_perdim_max_ms": 0, "suffix_scoring_ms": 0.366667, "cpu_readback_ms": 0.02},
        {"depth": 5, "partition_layout_ms": 0.253792, "histogram_ms": 9.32083, "histogram_perdim_max_ms": 0, "suffix_scoring_ms": 0.685166, "cpu_readback_ms": 0.036042}
      ],
      "iter_total_ms": 30.3526
    },
    {
      "iter": 21,
      "derivatives_ms": 0.19375,
      "init_partitions_ms": 0,
      "partition_layout_ms": 1.50621,
      "histogram_ms": 23.6494,
      "suffix_scoring_ms": 1.72371,
      "leaf_sums_ms": 0.257041,
      "leaf_values_ms": 0.346084,
      "tree_apply_ms": 0.27075,
      "loss_eval_ms": 0.251041,
      "cpu_readback_ms": 0.073793,
      "depth_stages": [
        {"depth": 0, "partition_layout_ms": 0.184125, "histogram_ms": 1.97525, "histogram_perdim_max_ms": 0, "suffix_scoring_ms": 0.080792, "cpu_readback_ms": 0.002959},
        {"depth": 1, "partition_layout_ms": 0.30025, "histogram_ms": 2.01583, "histogram_perdim_max_ms": 0, "suffix_scoring_ms": 0.091209, "cpu_readback_ms": 0.003167},
        {"depth": 2, "partition_layout_ms": 0.260875, "histogram_ms": 2.01662, "histogram_perdim_max_ms": 0, "suffix_scoring_ms": 0.143458, "cpu_readback_ms": 0.007083},
        {"depth": 3, "partition_layout_ms": 0.242459, "histogram_ms": 3.14096, "histogram_perdim_max_ms": 0, "suffix_scoring_ms": 0.223542, "cpu_readback_ms": 0.011292},
        {"depth": 4, "partition_layout_ms": 0.2695, "histogram_ms": 5.32479, "histogram_perdim_max_ms": 0, "suffix_scoring_ms": 0.379583, "cpu_readback_ms": 0.02},
        {"depth": 5, "partition_layout_ms": 0.249, "histogram_ms": 9.17592, "histogram_perdim_max_ms": 0, "suffix_scoring_ms": 0.805125, "cpu_readback_ms": 0.029292}
      ],
      "iter_total_ms": 29.6875
    },
    {
      "iter": 22,
      "derivatives_ms": 0.221292,
      "init_partitions_ms": 0,
      "partition_layout_ms": 1.40975,
      "histogram_ms": 23.828,
      "suffix_scoring_ms": 1.70162,
      "leaf_sums_ms": 0.21375,
      "leaf_values_ms": 0.227625,
      "tree_apply_ms": 0.225625,
      "loss_eval_ms": 0.251083,
      "cpu_readback_ms": 0.068376,
      "depth_stages": [
        {"depth": 0, "partition_layout_ms": 0.253667, "histogram_ms": 1.94225, "histogram_perdim_max_ms": 0, "suffix_scoring_ms": 0.075417, "cpu_readback_ms": 0.002917},
        {"depth": 1, "partition_layout_ms": 0.212042, "histogram_ms": 2.12042, "histogram_perdim_max_ms": 0, "suffix_scoring_ms": 0.103542, "cpu_readback_ms": 0.00375},
        {"depth": 2, "partition_layout_ms": 0.25125, "histogram_ms": 2.05163, "histogram_perdim_max_ms": 0, "suffix_scoring_ms": 0.130541, "cpu_readback_ms": 0.005375},
        {"depth": 3, "partition_layout_ms": 0.2615, "histogram_ms": 3.25208, "histogram_perdim_max_ms": 0, "suffix_scoring_ms": 0.222625, "cpu_readback_ms": 0.009917},
        {"depth": 4, "partition_layout_ms": 0.217583, "histogram_ms": 5.36129, "histogram_perdim_max_ms": 0, "suffix_scoring_ms": 0.393416, "cpu_readback_ms": 0.018625},
        {"depth": 5, "partition_layout_ms": 0.213708, "histogram_ms": 9.10033, "histogram_perdim_max_ms": 0, "suffix_scoring_ms": 0.776084, "cpu_readback_ms": 0.027792}
      ],
      "iter_total_ms": 29.6471
    },
    {
      "iter": 23,
      "derivatives_ms": 0.238958,
      "init_partitions_ms": 0,
      "partition_layout_ms": 1.51667,
      "histogram_ms": 23.7075,
      "suffix_scoring_ms": 1.67542,
      "leaf_sums_ms": 0.134541,
      "leaf_values_ms": 0.236459,
      "tree_apply_ms": 0.225708,
      "loss_eval_ms": 0.254,
      "cpu_readback_ms": 0.068791,
      "depth_stages": [
        {"depth": 0, "partition_layout_ms": 0.193334, "histogram_ms": 1.86862, "histogram_perdim_max_ms": 0, "suffix_scoring_ms": 0.071958, "cpu_readback_ms": 0.002},
        {"depth": 1, "partition_layout_ms": 0.355292, "histogram_ms": 1.9, "histogram_perdim_max_ms": 0, "suffix_scoring_ms": 0.085584, "cpu_readback_ms": 0.003041},
        {"depth": 2, "partition_layout_ms": 0.218041, "histogram_ms": 2.01304, "histogram_perdim_max_ms": 0, "suffix_scoring_ms": 0.120458, "cpu_readback_ms": 0.004958},
        {"depth": 3, "partition_layout_ms": 0.240417, "histogram_ms": 3.35425, "histogram_perdim_max_ms": 0, "suffix_scoring_ms": 0.215333, "cpu_readback_ms": 0.008542},
        {"depth": 4, "partition_layout_ms": 0.278208, "histogram_ms": 5.329, "histogram_perdim_max_ms": 0, "suffix_scoring_ms": 0.439709, "cpu_readback_ms": 0.015333},
        {"depth": 5, "partition_layout_ms": 0.231375, "histogram_ms": 9.24263, "histogram_perdim_max_ms": 0, "suffix_scoring_ms": 0.742375, "cpu_readback_ms": 0.034917}
      ],
      "iter_total_ms": 29.4716
    },
    {
      "iter": 24,
      "derivatives_ms": 0.205625,
      "init_partitions_ms": 0,
      "partition_layout_ms": 1.37925,
      "histogram_ms": 20.4902,
      "suffix_scoring_ms": 1.59496,
      "leaf_sums_ms": 0.252167,
      "leaf_values_ms": 0.247791,
      "tree_apply_ms": 0.231542,
      "loss_eval_ms": 0.26275,
      "cpu_readback_ms": 0.072041,
      "depth_stages": [
        {"depth": 0, "partition_layout_ms": 0.21225, "histogram_ms": 1.83808, "histogram_perdim_max_ms": 0, "suffix_scoring_ms": 0.071791, "cpu_readback_ms": 0.002083},
        {"depth": 1, "partition_layout_ms": 0.242375, "histogram_ms": 2.0615, "histogram_perdim_max_ms": 0, "suffix_scoring_ms": 0.088625, "cpu_readback_ms": 0.003125},
        {"depth": 2, "partition_layout_ms": 0.236084, "histogram_ms": 1.98596, "histogram_perdim_max_ms": 0, "suffix_scoring_ms": 0.120958, "cpu_readback_ms": 0.005042},
        {"depth": 3, "partition_layout_ms": 0.263417, "histogram_ms": 2.84425, "histogram_perdim_max_ms": 0, "suffix_scoring_ms": 0.187041, "cpu_readback_ms": 0.0085},
        {"depth": 4, "partition_layout_ms": 0.2235, "histogram_ms": 4.41188, "histogram_perdim_max_ms": 0, "suffix_scoring_ms": 0.37325, "cpu_readback_ms": 0.015875},
        {"depth": 5, "partition_layout_ms": 0.201625, "histogram_ms": 7.34854, "histogram_perdim_max_ms": 0, "suffix_scoring_ms": 0.753292, "cpu_readback_ms": 0.037416}
      ],
      "iter_total_ms": 26.324
    },
    {
      "iter": 25,
      "derivatives_ms": 0.240583,
      "init_partitions_ms": 0,
      "partition_layout_ms": 1.46121,
      "histogram_ms": 23.6968,
      "suffix_scoring_ms": 1.73675,
      "leaf_sums_ms": 0.226958,
      "leaf_values_ms": 0.210667,
      "tree_apply_ms": 0.2255,
      "loss_eval_ms": 0.2645,
      "cpu_readback_ms": 0.079668,
      "depth_stages": [
        {"depth": 0, "partition_layout_ms": 0.254375, "histogram_ms": 1.87204, "histogram_perdim_max_ms": 0, "suffix_scoring_ms": 0.093583, "cpu_readback_ms": 0.002333},
        {"depth": 1, "partition_layout_ms": 0.244542, "histogram_ms": 2.08883, "histogram_perdim_max_ms": 0, "suffix_scoring_ms": 0.094792, "cpu_readback_ms": 0.003334},
        {"depth": 2, "partition_layout_ms": 0.211125, "histogram_ms": 2.06717, "histogram_perdim_max_ms": 0, "suffix_scoring_ms": 0.126667, "cpu_readback_ms": 0.005209},
        {"depth": 3, "partition_layout_ms": 0.288875, "histogram_ms": 3.23687, "histogram_perdim_max_ms": 0, "suffix_scoring_ms": 0.219708, "cpu_readback_ms": 0.009958},
        {"depth": 4, "partition_layout_ms": 0.238791, "histogram_ms": 5.34383, "histogram_perdim_max_ms": 0, "suffix_scoring_ms": 0.413166, "cpu_readback_ms": 0.020917},
        {"depth": 5, "partition_layout_ms": 0.2235, "histogram_ms": 9.08808, "histogram_perdim_max_ms": 0, "suffix_scoring_ms": 0.788833, "cpu_readback_ms": 0.037917}
      ],
      "iter_total_ms": 29.859
    },
    {
      "iter": 26,
      "derivatives_ms": 0.247042,
      "init_partitions_ms": 0,
      "partition_layout_ms": 1.49075,
      "histogram_ms": 22.238,
      "suffix_scoring_ms": 1.51008,
      "leaf_sums_ms": 0.169959,
      "leaf_values_ms": 0.194083,
      "tree_apply_ms": 0.166458,
      "loss_eval_ms": 0.233291,
      "cpu_readback_ms": 0.065958,
      "depth_stages": [
        {"depth": 0, "partition_layout_ms": 0.395333, "histogram_ms": 2.02658, "histogram_perdim_max_ms": 0, "suffix_scoring_ms": 0.071083, "cpu_readback_ms": 0.002333},
        {"depth": 1, "partition_layout_ms": 0.209125, "histogram_ms": 1.96492, "histogram_perdim_max_ms": 0, "suffix_scoring_ms": 0.091166, "cpu_readback_ms": 0.002833},
        {"depth": 2, "partition_layout_ms": 0.211, "histogram_ms": 1.97842, "histogram_perdim_max_ms": 0, "suffix_scoring_ms": 0.120583, "cpu_readback_ms": 0.009542},
        {"depth": 3, "partition_layout_ms": 0.198833, "histogram_ms": 3.12513, "histogram_perdim_max_ms": 0, "suffix_scoring_ms": 0.192292, "cpu_readback_ms": 0.007292},
        {"depth": 4, "partition_layout_ms": 0.236917, "histogram_ms": 5.535, "histogram_perdim_max_ms": 0, "suffix_scoring_ms": 0.354333, "cpu_readback_ms": 0.017333},
        {"depth": 5, "partition_layout_ms": 0.239541, "histogram_ms": 7.60796, "histogram_perdim_max_ms": 0, "suffix_scoring_ms": 0.680625, "cpu_readback_ms": 0.026625}
      ],
      "iter_total_ms": 27.8659
    },
    {
      "iter": 27,
      "derivatives_ms": 0.234458,
      "init_partitions_ms": 0,
      "partition_layout_ms": 1.34475,
      "histogram_ms": 23.2152,
      "suffix_scoring_ms": 1.65275,
      "leaf_sums_ms": 0.391292,
      "leaf_values_ms": 0.267042,
      "tree_apply_ms": 0.192041,
      "loss_eval_ms": 0.261833,
      "cpu_readback_ms": 0.066372,
      "depth_stages": [
        {"depth": 0, "partition_layout_ms": 0.23475, "histogram_ms": 1.86604, "histogram_perdim_max_ms": 0, "suffix_scoring_ms": 0.073709, "cpu_readback_ms": 0.002708},
        {"depth": 1, "partition_layout_ms": 0.243583, "histogram_ms": 2.06021, "histogram_perdim_max_ms": 0, "suffix_scoring_ms": 0.094333, "cpu_readback_ms": 0.003208},
        {"depth": 2, "partition_layout_ms": 0.230417, "histogram_ms": 1.89383, "histogram_perdim_max_ms": 0, "suffix_scoring_ms": 0.132541, "cpu_readback_ms": 0.005291},
        {"depth": 3, "partition_layout_ms": 0.219, "histogram_ms": 3.25696, "histogram_perdim_max_ms": 0, "suffix_scoring_ms": 0.228375, "cpu_readback_ms": 0.009958},
        {"depth": 4, "partition_layout_ms": 0.220666, "histogram_ms": 5.25875, "histogram_perdim_max_ms": 0, "suffix_scoring_ms": 0.376542, "cpu_readback_ms": 0.016666},
        {"depth": 5, "partition_layout_ms": 0.196333, "histogram_ms": 8.87942, "histogram_perdim_max_ms": 0, "suffix_scoring_ms": 0.74725, "cpu_readback_ms": 0.028541}
      ],
      "iter_total_ms": 29.0338
    },
    {
      "iter": 28,
      "derivatives_ms": 0.22825,
      "init_partitions_ms": 0,
      "partition_layout_ms": 1.58158,
      "histogram_ms": 23.8253,
      "suffix_scoring_ms": 1.59183,
      "leaf_sums_ms": 0.226625,
      "leaf_values_ms": 0.202083,
      "tree_apply_ms": 0.17,
      "loss_eval_ms": 0.209417,
      "cpu_readback_ms": 0.071458,
      "depth_stages": [
        {"depth": 0, "partition_layout_ms": 0.211416, "histogram_ms": 1.88237, "histogram_perdim_max_ms": 0, "suffix_scoring_ms": 0.07375, "cpu_readback_ms": 0.002167},
        {"depth": 1, "partition_layout_ms": 0.238167, "histogram_ms": 2.09929, "histogram_perdim_max_ms": 0, "suffix_scoring_ms": 0.086708, "cpu_readback_ms": 0.004083},
        {"depth": 2, "partition_layout_ms": 0.24725, "histogram_ms": 2.04871, "histogram_perdim_max_ms": 0, "suffix_scoring_ms": 0.1215, "cpu_readback_ms": 0.004875},
        {"depth": 3, "partition_layout_ms": 0.365375, "histogram_ms": 3.39954, "histogram_perdim_max_ms": 0, "suffix_scoring_ms": 0.225959, "cpu_readback_ms": 0.010667},
        {"depth": 4, "partition_layout_ms": 0.255166, "histogram_ms": 5.13233, "histogram_perdim_max_ms": 0, "suffix_scoring_ms": 0.372709, "cpu_readback_ms": 0.0155},
        {"depth": 5, "partition_layout_ms": 0.264208, "histogram_ms": 9.26304, "histogram_perdim_max_ms": 0, "suffix_scoring_ms": 0.711209, "cpu_readback_ms": 0.034166}
      ],
      "iter_total_ms": 29.7169
    },
    {
      "iter": 29,
      "derivatives_ms": 0.218667,
      "init_partitions_ms": 0,
      "partition_layout_ms": 1.37163,
      "histogram_ms": 23.8095,
      "suffix_scoring_ms": 1.58937,
      "leaf_sums_ms": 0.19,
      "leaf_values_ms": 0.235042,
      "tree_apply_ms": 0.192417,
      "loss_eval_ms": 0.216042,
      "cpu_readback_ms": 0.071209,
      "depth_stages": [
        {"depth": 0, "partition_layout_ms": 0.237375, "histogram_ms": 1.93525, "histogram_perdim_max_ms": 0, "suffix_scoring_ms": 0.069667, "cpu_readback_ms": 0.003541},
        {"depth": 1, "partition_layout_ms": 0.220917, "histogram_ms": 2.02217, "histogram_perdim_max_ms": 0, "suffix_scoring_ms": 0.102333, "cpu_readback_ms": 0.003209},
        {"depth": 2, "partition_layout_ms": 0.228292, "histogram_ms": 2.07296, "histogram_perdim_max_ms": 0, "suffix_scoring_ms": 0.121042, "cpu_readback_ms": 0.004459},
        {"depth": 3, "partition_layout_ms": 0.227708, "histogram_ms": 3.37529, "histogram_perdim_max_ms": 0, "suffix_scoring_ms": 0.21, "cpu_readback_ms": 0.011},
        {"depth": 4, "partition_layout_ms": 0.222458, "histogram_ms": 5.08392, "histogram_perdim_max_ms": 0, "suffix_scoring_ms": 0.375208, "cpu_readback_ms": 0.019708},
        {"depth": 5, "partition_layout_ms": 0.234875, "histogram_ms": 9.31996, "histogram_perdim_max_ms": 0, "suffix_scoring_ms": 0.711125, "cpu_readback_ms": 0.029292}
      ],
      "iter_total_ms": 29.4376
    },
    {
      "iter": 30,
      "derivatives_ms": 0.206416,
      "init_partitions_ms": 0,
      "partition_layout_ms": 1.63821,
      "histogram_ms": 21.2252,
      "suffix_scoring_ms": 1.64721,
      "leaf_sums_ms": 0.223917,
      "leaf_values_ms": 0.199292,
      "tree_apply_ms": 0.201167,
      "loss_eval_ms": 0.223791,
      "cpu_readback_ms": 0.074291,
      "depth_stages": [
        {"depth": 0, "partition_layout_ms": 0.277292, "histogram_ms": 2.09071, "histogram_perdim_max_ms": 0, "suffix_scoring_ms": 0.076458, "cpu_readback_ms": 0.002417},
        {"depth": 1, "partition_layout_ms": 0.247667, "histogram_ms": 2.13754, "histogram_perdim_max_ms": 0, "suffix_scoring_ms": 0.101458, "cpu_readback_ms": 0.003333},
        {"depth": 2, "partition_layout_ms": 0.335541, "histogram_ms": 2.06792, "histogram_perdim_max_ms": 0, "suffix_scoring_ms": 0.128, "cpu_readback_ms": 0.00725},
        {"depth": 3, "partition_layout_ms": 0.233333, "histogram_ms": 3.26737, "histogram_perdim_max_ms": 0, "suffix_scoring_ms": 0.206583, "cpu_readback_ms": 0.017125},
        {"depth": 4, "partition_layout_ms": 0.266417, "histogram_ms": 4.03408, "histogram_perdim_max_ms": 0, "suffix_scoring_ms": 0.358791, "cpu_readback_ms": 0.013583},
        {"depth": 5, "partition_layout_ms": 0.277959, "histogram_ms": 7.62763, "histogram_perdim_max_ms": 0, "suffix_scoring_ms": 0.775917, "cpu_readback_ms": 0.030583}
      ],
      "iter_total_ms": 27.2743
    },
    {
      "iter": 31,
      "derivatives_ms": 0.205916,
      "init_partitions_ms": 0,
      "partition_layout_ms": 1.42012,
      "histogram_ms": 25.6395,
      "suffix_scoring_ms": 1.64817,
      "leaf_sums_ms": 0.202417,
      "leaf_values_ms": 0.2375,
      "tree_apply_ms": 0.212375,
      "loss_eval_ms": 0.238833,
      "cpu_readback_ms": 0.077874,
      "depth_stages": [
        {"depth": 0, "partition_layout_ms": 0.235333, "histogram_ms": 1.90162, "histogram_perdim_max_ms": 0, "suffix_scoring_ms": 0.077042, "cpu_readback_ms": 0.002833},
        {"depth": 1, "partition_layout_ms": 0.203583, "histogram_ms": 2.02817, "histogram_perdim_max_ms": 0, "suffix_scoring_ms": 0.09775, "cpu_readback_ms": 0.003},
        {"depth": 2, "partition_layout_ms": 0.202791, "histogram_ms": 2.03163, "histogram_perdim_max_ms": 0, "suffix_scoring_ms": 0.138291, "cpu_readback_ms": 0.007333},
        {"depth": 3, "partition_layout_ms": 0.269625, "histogram_ms": 3.23929, "histogram_perdim_max_ms": 0, "suffix_scoring_ms": 0.23025, "cpu_readback_ms": 0.012125},
        {"depth": 4, "partition_layout_ms": 0.267167, "histogram_ms": 7.20371, "histogram_perdim_max_ms": 0, "suffix_scoring_ms": 0.398958, "cpu_readback_ms": 0.017708},
        {"depth": 5, "partition_layout_ms": 0.241625, "histogram_ms": 9.23513, "histogram_perdim_max_ms": 0, "suffix_scoring_ms": 0.705875, "cpu_readback_ms": 0.034875}
      ],
      "iter_total_ms": 31.4158
    },
    {
      "iter": 32,
      "derivatives_ms": 0.220333,
      "init_partitions_ms": 0,
      "partition_layout_ms": 1.65738,
      "histogram_ms": 24.7004,
      "suffix_scoring_ms": 1.63888,
      "leaf_sums_ms": 0.184834,
      "leaf_values_ms": 0.213083,
      "tree_apply_ms": 0.217667,
      "loss_eval_ms": 0.230375,
      "cpu_readback_ms": 0.078751,
      "depth_stages": [
        {"depth": 0, "partition_layout_ms": 0.322625, "histogram_ms": 1.89413, "histogram_perdim_max_ms": 0, "suffix_scoring_ms": 0.085333, "cpu_readback_ms": 0.002333},
        {"depth": 1, "partition_layout_ms": 0.246209, "histogram_ms": 2.04125, "histogram_perdim_max_ms": 0, "suffix_scoring_ms": 0.1035, "cpu_readback_ms": 0.003209},
        {"depth": 2, "partition_layout_ms": 0.224708, "histogram_ms": 2.09175, "histogram_perdim_max_ms": 0, "suffix_scoring_ms": 0.123667, "cpu_readback_ms": 0.008875},
        {"depth": 3, "partition_layout_ms": 0.353417, "histogram_ms": 3.87087, "histogram_perdim_max_ms": 0, "suffix_scoring_ms": 0.218916, "cpu_readback_ms": 0.009667},
        {"depth": 4, "partition_layout_ms": 0.293416, "histogram_ms": 5.44058, "histogram_perdim_max_ms": 0, "suffix_scoring_ms": 0.3645, "cpu_readback_ms": 0.019458},
        {"depth": 5, "partition_layout_ms": 0.217, "histogram_ms": 9.36179, "histogram_perdim_max_ms": 0, "suffix_scoring_ms": 0.742959, "cpu_readback_ms": 0.035209}
      ],
      "iter_total_ms": 30.5486
    },
    {
      "iter": 33,
      "derivatives_ms": 0.20875,
      "init_partitions_ms": 0,
      "partition_layout_ms": 1.50696,
      "histogram_ms": 23.9184,
      "suffix_scoring_ms": 1.77538,
      "leaf_sums_ms": 0.226792,
      "leaf_values_ms": 0.219583,
      "tree_apply_ms": 0.192292,
      "loss_eval_ms": 0.234625,
      "cpu_readback_ms": 0.080584,
      "depth_stages": [
        {"depth": 0, "partition_layout_ms": 0.227541, "histogram_ms": 1.90596, "histogram_perdim_max_ms": 0, "suffix_scoring_ms": 0.080709, "cpu_readback_ms": 0.003292},
        {"depth": 1, "partition_layout_ms": 0.24575, "histogram_ms": 2.16767, "histogram_perdim_max_ms": 0, "suffix_scoring_ms": 0.096, "cpu_readback_ms": 0.003625},
        {"depth": 2, "partition_layout_ms": 0.303458, "histogram_ms": 2.06325, "histogram_perdim_max_ms": 0, "suffix_scoring_ms": 0.13725, "cpu_readback_ms": 0.004708},
        {"depth": 3, "partition_layout_ms": 0.23925, "histogram_ms": 3.07558, "histogram_perdim_max_ms": 0, "suffix_scoring_ms": 0.226, "cpu_readback_ms": 0.012417},
        {"depth": 4, "partition_layout_ms": 0.237167, "histogram_ms": 5.32496, "histogram_perdim_max_ms": 0, "suffix_scoring_ms": 0.409792, "cpu_readback_ms": 0.019417},
        {"depth": 5, "partition_layout_ms": 0.253791, "histogram_ms": 9.381, "histogram_perdim_max_ms": 0, "suffix_scoring_ms": 0.825625, "cpu_readback_ms": 0.037125}
      ],
      "iter_total_ms": 30.0918
    },
    {
      "iter": 34,
      "derivatives_ms": 0.243,
      "init_partitions_ms": 0,
      "partition_layout_ms": 1.42333,
      "histogram_ms": 23.7967,
      "suffix_scoring_ms": 1.74512,
      "leaf_sums_ms": 0.19725,
      "leaf_values_ms": 0.233458,
      "tree_apply_ms": 0.226,
      "loss_eval_ms": 0.236792,
      "cpu_readback_ms": 0.074584,
      "depth_stages": [
        {"depth": 0, "partition_layout_ms": 0.25925, "histogram_ms": 1.94837, "histogram_perdim_max_ms": 0, "suffix_scoring_ms": 0.079416, "cpu_readback_ms": 0.00275},
        {"depth": 1, "partition_layout_ms": 0.223584, "histogram_ms": 2.17504, "histogram_perdim_max_ms": 0, "suffix_scoring_ms": 0.100792, "cpu_readback_ms": 0.004792},
        {"depth": 2, "partition_layout_ms": 0.266833, "histogram_ms": 2.105, "histogram_perdim_max_ms": 0, "suffix_scoring_ms": 0.125458, "cpu_readback_ms": 0.006625},
        {"depth": 3, "partition_layout_ms": 0.222792, "histogram_ms": 3.35921, "histogram_perdim_max_ms": 0, "suffix_scoring_ms": 0.225208, "cpu_readback_ms": 0.009375},
        {"depth": 4, "partition_layout_ms": 0.24625, "histogram_ms": 5.11583, "histogram_perdim_max_ms": 0, "suffix_scoring_ms": 0.415709, "cpu_readback_ms": 0.016875},
        {"depth": 5, "partition_layout_ms": 0.204625, "histogram_ms": 9.09329, "histogram_perdim_max_ms": 0, "suffix_scoring_ms": 0.798542, "cpu_readback_ms": 0.034167}
      ],
      "iter_total_ms": 29.693
    },
    {
      "iter": 35,
      "derivatives_ms": 0.184917,
      "init_partitions_ms": 0,
      "partition_layout_ms": 1.46942,
      "histogram_ms": 24.36,
      "suffix_scoring_ms": 1.67329,
      "leaf_sums_ms": 0.25425,
      "leaf_values_ms": 0.25075,
      "tree_apply_ms": 0.224333,
      "loss_eval_ms": 0.284292,
      "cpu_readback_ms": 0.071126,
      "depth_stages": [
        {"depth": 0, "partition_layout_ms": 0.251917, "histogram_ms": 1.99263, "histogram_perdim_max_ms": 0, "suffix_scoring_ms": 0.085, "cpu_readback_ms": 0.004333},
        {"depth": 1, "partition_layout_ms": 0.264708, "histogram_ms": 2.02596, "histogram_perdim_max_ms": 0, "suffix_scoring_ms": 0.095125, "cpu_readback_ms": 0.003583},
        {"depth": 2, "partition_layout_ms": 0.2405, "histogram_ms": 2.04525, "histogram_perdim_max_ms": 0, "suffix_scoring_ms": 0.12675, "cpu_readback_ms": 0.006209},
        {"depth": 3, "partition_layout_ms": 0.22325, "histogram_ms": 3.21271, "histogram_perdim_max_ms": 0, "suffix_scoring_ms": 0.211834, "cpu_readback_ms": 0.009167},
        {"depth": 4, "partition_layout_ms": 0.269333, "histogram_ms": 5.3855, "histogram_perdim_max_ms": 0, "suffix_scoring_ms": 0.380917, "cpu_readback_ms": 0.019042},
        {"depth": 5, "partition_layout_ms": 0.219709, "histogram_ms": 9.698, "histogram_perdim_max_ms": 0, "suffix_scoring_ms": 0.773666, "cpu_readback_ms": 0.028792}
      ],
      "iter_total_ms": 30.259
    },
    {
      "iter": 36,
      "derivatives_ms": 0.268,
      "init_partitions_ms": 0,
      "partition_layout_ms": 1.40183,
      "histogram_ms": 21.8717,
      "suffix_scoring_ms": 1.74608,
      "leaf_sums_ms": 0.231084,
      "leaf_values_ms": 0.254875,
      "tree_apply_ms": 0.272459,
      "loss_eval_ms": 0.28225,
      "cpu_readback_ms": 0.071959,
      "depth_stages": [
        {"depth": 0, "partition_layout_ms": 0.241, "histogram_ms": 1.85383, "histogram_perdim_max_ms": 0, "suffix_scoring_ms": 0.082291, "cpu_readback_ms": 0.002375},
        {"depth": 1, "partition_layout_ms": 0.214833, "histogram_ms": 2.03854, "histogram_perdim_max_ms": 0, "suffix_scoring_ms": 0.1065, "cpu_readback_ms": 0.003209},
        {"depth": 2, "partition_layout_ms": 0.249125, "histogram_ms": 2.04471, "histogram_perdim_max_ms": 0, "suffix_scoring_ms": 0.144209, "cpu_readback_ms": 0.005208},
        {"depth": 3, "partition_layout_ms": 0.254334, "histogram_ms": 3.25017, "histogram_perdim_max_ms": 0, "suffix_scoring_ms": 0.222042, "cpu_readback_ms": 0.009625},
        {"depth": 4, "partition_layout_ms": 0.235334, "histogram_ms": 5.19058, "histogram_perdim_max_ms": 0, "suffix_scoring_ms": 0.41, "cpu_readback_ms": 0.0185},
        {"depth": 5, "partition_layout_ms": 0.207208, "histogram_ms": 7.49388, "histogram_perdim_max_ms": 0, "suffix_scoring_ms": 0.781041, "cpu_readback_ms": 0.033042}
      ],
      "iter_total_ms": 27.9624
    },
    {
      "iter": 37,
      "derivatives_ms": 0.231,
      "init_partitions_ms": 0,
      "partition_layout_ms": 1.47092,
      "histogram_ms": 23.1485,
      "suffix_scoring_ms": 1.69387,
      "leaf_sums_ms": 0.189708,
      "leaf_values_ms": 0.215792,
      "tree_apply_ms": 0.202833,
      "loss_eval_ms": 9.81638,
      "cpu_readback_ms": 0.081666,
      "depth_stages": [
        {"depth": 0, "partition_layout_ms": 0.263375, "histogram_ms": 2.02254, "histogram_perdim_max_ms": 0, "suffix_scoring_ms": 0.072833, "cpu_readback_ms": 0.002666},
        {"depth": 1, "partition_layout_ms": 0.216333, "histogram_ms": 2.03275, "histogram_perdim_max_ms": 0, "suffix_scoring_ms": 0.105833, "cpu_readback_ms": 0.00325},
        {"depth": 2, "partition_layout_ms": 0.249625, "histogram_ms": 2.01792, "histogram_perdim_max_ms": 0, "suffix_scoring_ms": 0.128209, "cpu_readback_ms": 0.005125},
        {"depth": 3, "partition_layout_ms": 0.233625, "histogram_ms": 3.23687, "histogram_perdim_max_ms": 0, "suffix_scoring_ms": 0.206, "cpu_readback_ms": 0.009417},
        {"depth": 4, "partition_layout_ms": 0.263667, "histogram_ms": 5.20171, "histogram_perdim_max_ms": 0, "suffix_scoring_ms": 0.398041, "cpu_readback_ms": 0.018458},
        {"depth": 5, "partition_layout_ms": 0.244292, "histogram_ms": 8.63671, "histogram_perdim_max_ms": 0, "suffix_scoring_ms": 0.782958, "cpu_readback_ms": 0.04275}
      ],
      "iter_total_ms": 38.4876
    },
    {
      "iter": 38,
      "derivatives_ms": 0.332291,
      "init_partitions_ms": 0,
      "partition_layout_ms": 1.33796,
      "histogram_ms": 23.0774,
      "suffix_scoring_ms": 1.79875,
      "leaf_sums_ms": 0.197584,
      "leaf_values_ms": 0.212,
      "tree_apply_ms": 0.189958,
      "loss_eval_ms": 0.214417,
      "cpu_readback_ms": 0.0765,
      "depth_stages": [
        {"depth": 0, "partition_layout_ms": 0.237583, "histogram_ms": 2.00175, "histogram_perdim_max_ms": 0, "suffix_scoring_ms": 0.083542, "cpu_readback_ms": 0.002375},
        {"depth": 1, "partition_layout_ms": 0.195417, "histogram_ms": 2.11788, "histogram_perdim_max_ms": 0, "suffix_scoring_ms": 0.090792, "cpu_readback_ms": 0.006125},
        {"depth": 2, "partition_layout_ms": 0.231292, "histogram_ms": 1.98417, "histogram_perdim_max_ms": 0, "suffix_scoring_ms": 0.131291, "cpu_readback_ms": 0.0045},
        {"depth": 3, "partition_layout_ms": 0.20575, "histogram_ms": 3.28979, "histogram_perdim_max_ms": 0, "suffix_scoring_ms": 0.2185, "cpu_readback_ms": 0.008292},
        {"depth": 4, "partition_layout_ms": 0.2375, "histogram_ms": 5.136, "histogram_perdim_max_ms": 0, "suffix_scoring_ms": 0.459458, "cpu_readback_ms": 0.025083},
        {"depth": 5, "partition_layout_ms": 0.230417, "histogram_ms": 8.54779, "histogram_perdim_max_ms": 0, "suffix_scoring_ms": 0.815166, "cpu_readback_ms": 0.030125}
      ],
      "iter_total_ms": 28.924
    },
    {
      "iter": 39,
      "derivatives_ms": 0.219333,
      "init_partitions_ms": 0,
      "partition_layout_ms": 1.55992,
      "histogram_ms": 23.8684,
      "suffix_scoring_ms": 1.56171,
      "leaf_sums_ms": 0.172917,
      "leaf_values_ms": 0.21125,
      "tree_apply_ms": 0.198583,
      "loss_eval_ms": 0.2885,
      "cpu_readback_ms": 0.073375,
      "depth_stages": [
        {"depth": 0, "partition_layout_ms": 0.253875, "histogram_ms": 1.82342, "histogram_perdim_max_ms": 0, "suffix_scoring_ms": 0.081791, "cpu_readback_ms": 0.002042},
        {"depth": 1, "partition_layout_ms": 0.193709, "histogram_ms": 1.98375, "histogram_perdim_max_ms": 0, "suffix_scoring_ms": 0.092583, "cpu_readback_ms": 0.003125},
        {"depth": 2, "partition_layout_ms": 0.308834, "histogram_ms": 2.15454, "histogram_perdim_max_ms": 0, "suffix_scoring_ms": 0.136166, "cpu_readback_ms": 0.005667},
        {"depth": 3, "partition_layout_ms": 0.220125, "histogram_ms": 3.30417, "histogram_perdim_max_ms": 0, "suffix_scoring_ms": 0.230042, "cpu_readback_ms": 0.011541},
        {"depth": 4, "partition_layout_ms": 0.227584, "histogram_ms": 5.20092, "histogram_perdim_max_ms": 0, "suffix_scoring_ms": 0.369334, "cpu_readback_ms": 0.01725},
        {"depth": 5, "partition_layout_ms": 0.355792, "histogram_ms": 9.40162, "histogram_perdim_max_ms": 0, "suffix_scoring_ms": 0.651792, "cpu_readback_ms": 0.03375}
      ],
      "iter_total_ms": 29.5333
    },
    {
      "iter": 40,
      "derivatives_ms": 0.206584,
      "init_partitions_ms": 0,
      "partition_layout_ms": 1.98621,
      "histogram_ms": 24.9722,
      "suffix_scoring_ms": 1.59008,
      "leaf_sums_ms": 0.2025,
      "leaf_values_ms": 0.218083,
      "tree_apply_ms": 0.295208,
      "loss_eval_ms": 0.275208,
      "cpu_readback_ms": 0.089582,
      "depth_stages": [
        {"depth": 0, "partition_layout_ms": 0.217708, "histogram_ms": 2.00558, "histogram_perdim_max_ms": 0, "suffix_scoring_ms": 0.070583, "cpu_readback_ms": 0.003625},
        {"depth": 1, "partition_layout_ms": 0.295917, "histogram_ms": 2.27692, "histogram_perdim_max_ms": 0, "suffix_scoring_ms": 0.114916, "cpu_readback_ms": 0.007042},
        {"depth": 2, "partition_layout_ms": 0.428541, "histogram_ms": 2.34579, "histogram_perdim_max_ms": 0, "suffix_scoring_ms": 0.125625, "cpu_readback_ms": 0.009791},
        {"depth": 3, "partition_layout_ms": 0.250417, "histogram_ms": 3.49758, "histogram_perdim_max_ms": 0, "suffix_scoring_ms": 0.223791, "cpu_readback_ms": 0.00975},
        {"depth": 4, "partition_layout_ms": 0.559083, "histogram_ms": 5.44983, "histogram_perdim_max_ms": 0, "suffix_scoring_ms": 0.357875, "cpu_readback_ms": 0.019708},
        {"depth": 5, "partition_layout_ms": 0.234542, "histogram_ms": 9.39654, "histogram_perdim_max_ms": 0, "suffix_scoring_ms": 0.697292, "cpu_readback_ms": 0.039666}
      ],
      "iter_total_ms": 31.6905
    },
    {
      "iter": 41,
      "derivatives_ms": 0.261208,
      "init_partitions_ms": 0,
      "partition_layout_ms": 1.46396,
      "histogram_ms": 23.438,
      "suffix_scoring_ms": 1.62846,
      "leaf_sums_ms": 0.19075,
      "leaf_values_ms": 0.228667,
      "tree_apply_ms": 0.189334,
      "loss_eval_ms": 0.230709,
      "cpu_readback_ms": 0.078499,
      "depth_stages": [
        {"depth": 0, "partition_layout_ms": 0.261417, "histogram_ms": 2.08046, "histogram_perdim_max_ms": 0, "suffix_scoring_ms": 0.074875, "cpu_readback_ms": 0.002625},
        {"depth": 1, "partition_layout_ms": 0.291583, "histogram_ms": 2.07388, "histogram_perdim_max_ms": 0, "suffix_scoring_ms": 0.088167, "cpu_readback_ms": 0.007166},
        {"depth": 2, "partition_layout_ms": 0.21725, "histogram_ms": 2.10958, "histogram_perdim_max_ms": 0, "suffix_scoring_ms": 0.122, "cpu_readback_ms": 0.006458},
        {"depth": 3, "partition_layout_ms": 0.269, "histogram_ms": 3.25329, "histogram_perdim_max_ms": 0, "suffix_scoring_ms": 0.201167, "cpu_readback_ms": 0.009958},
        {"depth": 4, "partition_layout_ms": 0.220583, "histogram_ms": 5.40883, "histogram_perdim_max_ms": 0, "suffix_scoring_ms": 0.386, "cpu_readback_ms": 0.014667},
        {"depth": 5, "partition_layout_ms": 0.204125, "histogram_ms": 8.512, "histogram_perdim_max_ms": 0, "suffix_scoring_ms": 0.75625, "cpu_readback_ms": 0.037625}
      ],
      "iter_total_ms": 29.1379
    },
    {
      "iter": 42,
      "derivatives_ms": 0.251667,
      "init_partitions_ms": 0,
      "partition_layout_ms": 1.92875,
      "histogram_ms": 24.5023,
      "suffix_scoring_ms": 1.66721,
      "leaf_sums_ms": 0.285291,
      "leaf_values_ms": 0.2395,
      "tree_apply_ms": 0.210042,
      "loss_eval_ms": 0.275417,
      "cpu_readback_ms": 0.082833,
      "depth_stages": [
        {"depth": 0, "partition_layout_ms": 0.247209, "histogram_ms": 2.04513, "histogram_perdim_max_ms": 0, "suffix_scoring_ms": 0.072291, "cpu_readback_ms": 0.0045},
        {"depth": 1, "partition_layout_ms": 0.338667, "histogram_ms": 2.16317, "histogram_perdim_max_ms": 0, "suffix_scoring_ms": 0.091125, "cpu_readback_ms": 0.009042},
        {"depth": 2, "partition_layout_ms": 0.272041, "histogram_ms": 2.11738, "histogram_perdim_max_ms": 0, "suffix_scoring_ms": 0.125666, "cpu_readback_ms": 0.007958},
        {"depth": 3, "partition_layout_ms": 0.227583, "histogram_ms": 3.43721, "histogram_perdim_max_ms": 0, "suffix_scoring_ms": 0.198375, "cpu_readback_ms": 0.008375},
        {"depth": 4, "partition_layout_ms": 0.255917, "histogram_ms": 5.54758, "histogram_perdim_max_ms": 0, "suffix_scoring_ms": 0.393708, "cpu_readback_ms": 0.019333},
        {"depth": 5, "partition_layout_ms": 0.587333, "histogram_ms": 9.19179, "histogram_perdim_max_ms": 0, "suffix_scoring_ms": 0.786041, "cpu_readback_ms": 0.033625}
      ],
      "iter_total_ms": 31.1542
    },
    {
      "iter": 43,
      "derivatives_ms": 0.264459,
      "init_partitions_ms": 0,
      "partition_layout_ms": 1.67771,
      "histogram_ms": 24.3218,
      "suffix_scoring_ms": 1.62288,
      "leaf_sums_ms": 0.191917,
      "leaf_values_ms": 0.373416,
      "tree_apply_ms": 0.25175,
      "loss_eval_ms": 0.246125,
      "cpu_readback_ms": 0.07425,
      "depth_stages": [
        {"depth": 0, "partition_layout_ms": 0.339958, "histogram_ms": 1.9365, "histogram_perdim_max_ms": 0, "suffix_scoring_ms": 0.0815, "cpu_readback_ms": 0.0035},
        {"depth": 1, "partition_layout_ms": 0.213542, "histogram_ms": 2.14417, "histogram_perdim_max_ms": 0, "suffix_scoring_ms": 0.094083, "cpu_readback_ms": 0.005791},
        {"depth": 2, "partition_layout_ms": 0.322459, "histogram_ms": 2.09342, "histogram_perdim_max_ms": 0, "suffix_scoring_ms": 0.139667, "cpu_readback_ms": 0.005167},
        {"depth": 3, "partition_layout_ms": 0.276, "histogram_ms": 3.19212, "histogram_perdim_max_ms": 0, "suffix_scoring_ms": 0.206166, "cpu_readback_ms": 0.008625},
        {"depth": 4, "partition_layout_ms": 0.236375, "histogram_ms": 5.39388, "histogram_perdim_max_ms": 0, "suffix_scoring_ms": 0.374834, "cpu_readback_ms": 0.024042},
        {"depth": 5, "partition_layout_ms": 0.289375, "histogram_ms": 9.56171, "histogram_perdim_max_ms": 0, "suffix_scoring_ms": 0.726625, "cpu_readback_ms": 0.027125}
      ],
      "iter_total_ms": 30.6478
    },
    {
      "iter": 44,
      "derivatives_ms": 0.201417,
      "init_partitions_ms": 0,
      "partition_layout_ms": 1.43137,
      "histogram_ms": 24.9058,
      "suffix_scoring_ms": 1.60225,
      "leaf_sums_ms": 0.256541,
      "leaf_values_ms": 0.312709,
      "tree_apply_ms": 0.239375,
      "loss_eval_ms": 0.23575,
      "cpu_readback_ms": 0.072293,
      "depth_stages": [
        {"depth": 0, "partition_layout_ms": 0.210291, "histogram_ms": 1.95525, "histogram_perdim_max_ms": 0, "suffix_scoring_ms": 0.084583, "cpu_readback_ms": 0.002542},
        {"depth": 1, "partition_layout_ms": 0.259291, "histogram_ms": 2.051, "histogram_perdim_max_ms": 0, "suffix_scoring_ms": 0.100292, "cpu_readback_ms": 0.004042},
        {"depth": 2, "partition_layout_ms": 0.244959, "histogram_ms": 2.16421, "histogram_perdim_max_ms": 0, "suffix_scoring_ms": 0.142083, "cpu_readback_ms": 0.005334},
        {"depth": 3, "partition_layout_ms": 0.241333, "histogram_ms": 3.45125, "histogram_perdim_max_ms": 0, "suffix_scoring_ms": 0.210792, "cpu_readback_ms": 0.009917},
        {"depth": 4, "partition_layout_ms": 0.254, "histogram_ms": 5.68496, "histogram_perdim_max_ms": 0, "suffix_scoring_ms": 0.362583, "cpu_readback_ms": 0.017875},
        {"depth": 5, "partition_layout_ms": 0.2215, "histogram_ms": 9.59913, "histogram_perdim_max_ms": 0, "suffix_scoring_ms": 0.701917, "cpu_readback_ms": 0.032583}
      ],
      "iter_total_ms": 30.8084
    },
    {
      "iter": 45,
      "derivatives_ms": 0.258708,
      "init_partitions_ms": 0,
      "partition_layout_ms": 1.46175,
      "histogram_ms": 21.0165,
      "suffix_scoring_ms": 1.59983,
      "leaf_sums_ms": 0.214833,
      "leaf_values_ms": 0.2025,
      "tree_apply_ms": 0.237834,
      "loss_eval_ms": 0.326125,
      "cpu_readback_ms": 0.078959,
      "depth_stages": [
        {"depth": 0, "partition_layout_ms": 0.310792, "histogram_ms": 2.10012, "histogram_perdim_max_ms": 0, "suffix_scoring_ms": 0.082125, "cpu_readback_ms": 0.004791},
        {"depth": 1, "partition_layout_ms": 0.222667, "histogram_ms": 2.10825, "histogram_perdim_max_ms": 0, "suffix_scoring_ms": 0.087958, "cpu_readback_ms": 0.003625},
        {"depth": 2, "partition_layout_ms": 0.231, "histogram_ms": 2.068, "histogram_perdim_max_ms": 0, "suffix_scoring_ms": 0.138209, "cpu_readback_ms": 0.006917},
        {"depth": 3, "partition_layout_ms": 0.26525, "histogram_ms": 3.12075, "histogram_perdim_max_ms": 0, "suffix_scoring_ms": 0.201875, "cpu_readback_ms": 0.009625},
        {"depth": 4, "partition_layout_ms": 0.203166, "histogram_ms": 4.11867, "histogram_perdim_max_ms": 0, "suffix_scoring_ms": 0.362209, "cpu_readback_ms": 0.015667},
        {"depth": 5, "partition_layout_ms": 0.228875, "histogram_ms": 7.50071, "histogram_perdim_max_ms": 0, "suffix_scoring_ms": 0.727458, "cpu_readback_ms": 0.038334}
      ],
      "iter_total_ms": 27.095
    },
    {
      "iter": 46,
      "derivatives_ms": 0.268584,
      "init_partitions_ms": 0,
      "partition_layout_ms": 1.47625,
      "histogram_ms": 24.3377,
      "suffix_scoring_ms": 1.71967,
      "leaf_sums_ms": 0.255834,
      "leaf_values_ms": 0.225416,
      "tree_apply_ms": 0.263542,
      "loss_eval_ms": 0.262292,
      "cpu_readback_ms": 0.085043,
      "depth_stages": [
        {"depth": 0, "partition_layout_ms": 0.2335, "histogram_ms": 2.26867, "histogram_perdim_max_ms": 0, "suffix_scoring_ms": 0.081584, "cpu_readback_ms": 0.003625},
        {"depth": 1, "partition_layout_ms": 0.2245, "histogram_ms": 2.08962, "histogram_perdim_max_ms": 0, "suffix_scoring_ms": 0.088042, "cpu_readback_ms": 0.003709},
        {"depth": 2, "partition_layout_ms": 0.265042, "histogram_ms": 2.09842, "histogram_perdim_max_ms": 0, "suffix_scoring_ms": 0.136625, "cpu_readback_ms": 0.005042},
        {"depth": 3, "partition_layout_ms": 0.268959, "histogram_ms": 3.52683, "histogram_perdim_max_ms": 0, "suffix_scoring_ms": 0.237, "cpu_readback_ms": 0.012208},
        {"depth": 4, "partition_layout_ms": 0.228334, "histogram_ms": 5.14963, "histogram_perdim_max_ms": 0, "suffix_scoring_ms": 0.404916, "cpu_readback_ms": 0.021334},
        {"depth": 5, "partition_layout_ms": 0.255917, "histogram_ms": 9.2045, "histogram_perdim_max_ms": 0, "suffix_scoring_ms": 0.7715, "cpu_readback_ms": 0.039125}
      ],
      "iter_total_ms": 30.4674
    },
    {
      "iter": 47,
      "derivatives_ms": 0.188,
      "init_partitions_ms": 0,
      "partition_layout_ms": 1.45879,
      "histogram_ms": 24.842,
      "suffix_scoring_ms": 1.69454,
      "leaf_sums_ms": 0.237708,
      "leaf_values_ms": 0.215084,
      "tree_apply_ms": 0.212167,
      "loss_eval_ms": 0.242792,
      "cpu_readback_ms": 0.085042,
      "depth_stages": [
        {"depth": 0, "partition_layout_ms": 0.278291, "histogram_ms": 2.123, "histogram_perdim_max_ms": 0, "suffix_scoring_ms": 0.077, "cpu_readback_ms": 0.002667},
        {"depth": 1, "partition_layout_ms": 0.259375, "histogram_ms": 2.04942, "histogram_perdim_max_ms": 0, "suffix_scoring_ms": 0.098417, "cpu_readback_ms": 0.003875},
        {"depth": 2, "partition_layout_ms": 0.232958, "histogram_ms": 2.15146, "histogram_perdim_max_ms": 0, "suffix_scoring_ms": 0.140666, "cpu_readback_ms": 0.00625},
        {"depth": 3, "partition_layout_ms": 0.174833, "histogram_ms": 3.47433, "histogram_perdim_max_ms": 0, "suffix_scoring_ms": 0.201833, "cpu_readback_ms": 0.013833},
        {"depth": 4, "partition_layout_ms": 0.261333, "histogram_ms": 5.18158, "histogram_perdim_max_ms": 0, "suffix_scoring_ms": 0.392292, "cpu_readback_ms": 0.019167},
        {"depth": 5, "partition_layout_ms": 0.252, "histogram_ms": 9.86225, "histogram_perdim_max_ms": 0, "suffix_scoring_ms": 0.784333, "cpu_readback_ms": 0.03925}
      ],
      "iter_total_ms": 30.8796
    },
    {
      "iter": 48,
      "derivatives_ms": 0.187042,
      "init_partitions_ms": 0,
      "partition_layout_ms": 1.45529,
      "histogram_ms": 23.7419,
      "suffix_scoring_ms": 1.79854,
      "leaf_sums_ms": 0.19525,
      "leaf_values_ms": 0.214625,
      "tree_apply_ms": 0.187709,
      "loss_eval_ms": 0.233292,
      "cpu_readback_ms": 0.086834,
      "depth_stages": [
        {"depth": 0, "partition_layout_ms": 0.265958, "histogram_ms": 2.05467, "histogram_perdim_max_ms": 0, "suffix_scoring_ms": 0.075167, "cpu_readback_ms": 0.002416},
        {"depth": 1, "partition_layout_ms": 0.216, "histogram_ms": 2.16208, "histogram_perdim_max_ms": 0, "suffix_scoring_ms": 0.09525, "cpu_readback_ms": 0.004917},
        {"depth": 2, "partition_layout_ms": 0.2385, "histogram_ms": 2.06375, "histogram_perdim_max_ms": 0, "suffix_scoring_ms": 0.135584, "cpu_readback_ms": 0.0075},
        {"depth": 3, "partition_layout_ms": 0.260417, "histogram_ms": 3.23925, "histogram_perdim_max_ms": 0, "suffix_scoring_ms": 0.235084, "cpu_readback_ms": 0.008917},
        {"depth": 4, "partition_layout_ms": 0.245792, "histogram_ms": 5.30454, "histogram_perdim_max_ms": 0, "suffix_scoring_ms": 0.419417, "cpu_readback_ms": 0.01875},
        {"depth": 5, "partition_layout_ms": 0.228625, "histogram_ms": 8.91762, "histogram_perdim_max_ms": 0, "suffix_scoring_ms": 0.838042, "cpu_readback_ms": 0.044334}
      ],
      "iter_total_ms": 29.7687
    },
    {
      "iter": 49,
      "derivatives_ms": 0.20725,
      "init_partitions_ms": 0,
      "partition_layout_ms": 1.51963,
      "histogram_ms": 23.5229,
      "suffix_scoring_ms": 1.65529,
      "leaf_sums_ms": 0.209125,
      "leaf_values_ms": 0.191042,
      "tree_apply_ms": 0.213625,
      "loss_eval_ms": 0.228875,
      "cpu_readback_ms": 0.077665,
      "depth_stages": [
        {"depth": 0, "partition_layout_ms": 0.233292, "histogram_ms": 1.91646, "histogram_perdim_max_ms": 0, "suffix_scoring_ms": 0.086541, "cpu_readback_ms": 0.002},
        {"depth": 1, "partition_layout_ms": 0.257458, "histogram_ms": 2.02633, "histogram_perdim_max_ms": 0, "suffix_scoring_ms": 0.099959, "cpu_readback_ms": 0.00675},
        {"depth": 2, "partition_layout_ms": 0.218333, "histogram_ms": 1.96217, "histogram_perdim_max_ms": 0, "suffix_scoring_ms": 0.118958, "cpu_readback_ms": 0.007333},
        {"depth": 3, "partition_layout_ms": 0.225625, "histogram_ms": 3.12996, "histogram_perdim_max_ms": 0, "suffix_scoring_ms": 0.205125, "cpu_readback_ms": 0.009833},
        {"depth": 4, "partition_layout_ms": 0.235458, "histogram_ms": 5.34725, "histogram_perdim_max_ms": 0, "suffix_scoring_ms": 0.404458, "cpu_readback_ms": 0.018666},
        {"depth": 5, "partition_layout_ms": 0.349459, "histogram_ms": 9.14071, "histogram_perdim_max_ms": 0, "suffix_scoring_ms": 0.74025, "cpu_readback_ms": 0.033083}
      ],
      "iter_total_ms": 29.364
    }
  ]
}
